llamafirewall/BUCK
llamafirewall/__init__.py
llamafirewall/config.py
llamafirewall/llamafirewall.py
llamafirewall/llamafirewall_data_types.py
llamafirewall/cli/BUCK
llamafirewall/cli/__init__.py
llamafirewall/cli/configure.py
llamafirewall/scanners/BUCK
llamafirewall/scanners/__init__.py
llamafirewall/scanners/base_scanner.py
llamafirewall/scanners/code_shield_scanner.py
llamafirewall/scanners/custom_check_scanner.py
llamafirewall/scanners/hidden_ascii_scanner.py
llamafirewall/scanners/prompt_guard_scanner.py
llamafirewall/scanners/promptguard_utils.py
llamafirewall/scanners/regex_scanner.py
llamafirewall/scanners/experimental/BUCK
llamafirewall/scanners/experimental/__init__.py
llamafirewall/scanners/experimental/alignmentcheck_scanner.py
llamafirewall/scanners/experimental/piicheck_scanner.py
llamafirewall/utils/BUCK
llamafirewall/utils/__init__.py
llamafirewall/utils/base_llm.py
llamafirewall-1.0.3.dist-info/METADATA
llamafirewall-1.0.3.dist-info/WHEEL
llamafirewall-1.0.3.dist-info/entry_points.txt
llamafirewall-1.0.3.dist-info/licenses/LICENSE
llamafirewall-1.0.3.dist-info/RECORD
